{
  "dataset": "GeoRank countries dataset",
  "version": "0.2",
  "created": "2026-06-17",
  "countries": 191,
  "rules": [
    "UN member states only",
    "territories excluded",
    "South Africa and Bolivia excluded",
    "countries with multiple capital ambiguity excluded",
    "gameplay uses frozen local JSON"
  ],
  "updates": [
    "Added coastlineKm",
    "Added highestPointM",
    "Added highestPointName"
  ],
  "sources": {
    "base": "Existing GeoRank v0.1 country file derived from countryinfo/manual seed values",
    "coastline": "LSYS/country-coastline-distance coastlines.csv, coastline_wf from CIA World Factbook",
    "highestPoint": "Flagpedia highest-point list cross-checked conceptually against Wikipedia elevation-extremes table"
  },
  "notes": [
    "Coastline values vary by source; GeoRank freezes coastline_wf for consistency.",
    "Highest-point values are game-source values; some disputed countries/high points use the frozen source ranking."
  ]
}